xmlvalidator/__init__.py
xmlvalidator/xml_validator_results.py
xmlvalidator/xml_validator_utils.py
xmlvalidator/XmlValidator.py
robotframework_xmlvalidator-2.0.0.dist-info/LICENSE
robotframework_xmlvalidator-2.0.0.dist-info/METADATA
robotframework_xmlvalidator-2.0.0.dist-info/WHEEL
robotframework_xmlvalidator-2.0.0.dist-info/RECORD
