Metadata-Version: 2.3
Name: robotframework-xmlvalidator
Version: 2.0.0
Summary: A Robot Framework test library for validating XML files against XSD schemas
License: Apache-2.0
Keywords: robotframework,xml,xsd,validation,test-library,test,testing,test-automation
Author: Michael Hallik
Author-email: hallik.michael@gmail.com
Requires-Python: >=3.10
Classifier: Framework :: Robot Framework
Classifier: License :: OSI Approved :: Apache Software License
Classifier: Programming Language :: Python :: 3
Classifier: Programming Language :: Python :: 3.10
Classifier: Programming Language :: Python :: 3.11
Classifier: Programming Language :: Python :: 3.12
Classifier: Programming Language :: Python :: 3.13
Classifier: Programming Language :: Python :: 3 :: Only
Classifier: Topic :: Software Development :: Testing
Requires-Dist: lxml (>=5.1.0,<6.0.0)
Requires-Dist: pandas (>=2.2.0,<3.0.0)
Requires-Dist: robotframework (>=7.0.0,<8.0.0)
Requires-Dist: xmlschema (>=3.4.3,<4.0.0)
Project-URL: Documentation, https://github.com/MichaelHallik/robotframework-xmlvalidator#readme
Project-URL: Homepage, https://github.com/MichaelHallik/robotframework-xmlvalidator
Project-URL: Repository, https://github.com/MichaelHallik/robotframework-xmlvalidator
